{"LevelData":{"Time":null,"LevelScaleFactor":1,"ParkingSpaceInit":4,"GuestColor":[11,11,11,11,6,6,6,6,5,5,5,5,11,11,11,11,7,7,7,7,7,7,7,7,7,7,5,5,5,5,5,5,4,4,4,4,4,4,7,7,7,7,7,7,12,12,12,12,8,8,8,8,8,8,7,7,7,7,7,7,6,6,6,6,6,6,8,8,8,8,8,8,8,8,8,8,8,8,8,8,8,8,2,2,2,2,2,2,6,6,6,6,6,6,6,6,6,6,7,7,7,7,7,7,7,7,7,7,8,8,8,8,8,8,8,8,8,8,2,2,2,2,2,2,11,11,11,11,5,5,5,5,5,5,1,1,1,1,1,1,3,3,3,3,3,3,3,3,3,3,3,3,4,4,4,4,4,4,11,11,11,11,2,2,2,2,4,4,4,4,4,4,1,1,1,1,1,1,4,4,4,4,4,4,4,4,4,4,4,4,11,11,11,11,2,2,2,2,2,2,4,4,4,4,4,4,2,2,2,2,2,2,1,1,1,1,1,1,3,3,3,3,11,11,11,11,2,2,2,2,2,2,4,4,4,4,4,4,3,3,3,3,3,3,3,3,3,3,3,3,2,2,2,2,2,2,2,2,2,2,2,2,4,4,4,4,4,4,7,7,7,7,1,1,1,1,1,1,4,4,4,4,4,4],"CarInfo":[{"idCar":59,"carColor":11,"carSize":0,"carPosition":{"x":-3.688661080819589,"y":-7.040614940502025,"z":0},"carDirection":6},{"idCar":58,"carColor":6,"carSize":0,"carPosition":{"x":-1.7864453351056133,"y":-5.086734913013599,"z":0},"carDirection":6},{"idCar":57,"carColor":5,"carSize":0,"carPosition":{"x":-0.18226001880787035,"y":-5.086737173574942,"z":0},"carDirection":6},{"idCar":56,"carColor":11,"carSize":0,"carPosition":{"x":1.4329251889829282,"y":-5.086738303855613,"z":0},"carDirection":6},{"idCar":55,"carColor":7,"carSize":2,"carPosition":{"x":1.23492431640625,"y":-6.096923262984664,"z":0},"carDirection":6},{"idCar":54,"carColor":5,"carSize":1,"carPosition":{"x":2.9814814814814814,"y":-5.62962962962963,"z":0},"carDirection":0},{"idCar":53,"carColor":4,"carSize":1,"carPosition":{"x":2.1149269386574074,"y":-3.3817409939236107,"z":0},"carDirection":2},{"idCar":52,"carColor":7,"carSize":1,"carPosition":{"x":2.070926242404514,"y":-4.261739095052083,"z":0},"carDirection":2},{"idCar":51,"carColor":12,"carSize":0,"carPosition":{"x":0.7197412561487269,"y":-3.8217389142071756,"z":0},"carDirection":0},{"idCar":50,"carColor":8,"carSize":1,"carPosition":{"x":-0.6864437527126735,"y":-3.3817364728009256,"z":0},"carDirection":2},{"idCar":49,"carColor":7,"carSize":1,"carPosition":{"x":-0.6754444263599537,"y":-4.261736269350405,"z":0},"carDirection":2},{"idCar":48,"carColor":6,"carSize":1,"carPosition":{"x":-2.1366294578269676,"y":-3.832736545138889,"z":0},"carDirection":0},{"idCar":47,"carColor":8,"carSize":2,"carPosition":{"x":-1.3482609501591434,"y":-6.096921567563657,"z":0},"carDirection":2},{"idCar":46,"carColor":8,"carSize":1,"carPosition":{"x":-3.0936310379593457,"y":-5.78891838921441,"z":0},"carDirection":0},{"idCar":45,"carColor":2,"carSize":1,"carPosition":{"x":-3.0166292543764466,"y":-3.8327342845775463,"z":0},"carDirection":0},{"idCar":44,"carColor":6,"carSize":2,"carPosition":{"x":2.023297910337095,"y":-2.5127393934461804,"z":0},"carDirection":2},{"idCar":43,"carColor":7,"carSize":2,"carPosition":{"x":-0.6442577220775463,"y":-2.512737132884838,"z":0},"carDirection":2},{"idCar":42,"carColor":8,"carSize":0,"carPosition":{"x":-2.7636275114836515,"y":-2.5347357855902777,"z":0},"carDirection":2},{"idCar":41,"carColor":8,"carSize":1,"carPosition":{"x":0.6739287199797453,"y":-1.4457374855324072,"z":0},"carDirection":6},{"idCar":39,"carColor":2,"carSize":1,"carPosition":{"x":2.2579289189091436,"y":-1.44573974609375,"z":0},"carDirection":6},{"idCar":37,"carColor":11,"carSize":0,"carPosition":{"x":-0.17307027180989581,"y":-0.5987367983217592,"z":0},"carDirection":6},{"idCar":34,"carColor":5,"carSize":1,"carPosition":{"x":-0.9760713930483217,"y":-1.445736355251736,"z":0},"carDirection":2},{"idCar":32,"carColor":1,"carSize":1,"carPosition":{"x":-2.604071157949942,"y":-1.4457340946903934,"z":0},"carDirection":2},{"idCar":31,"carColor":3,"carSize":1,"carPosition":{"x":-3.9406277691876443,"y":-2.611732765480324,"z":0},"carDirection":4},{"idCar":30,"carColor":3,"carSize":1,"carPosition":{"x":3.9464812102141202,"y":-4.37911139594184,"z":0},"carDirection":0},{"idCar":29,"carColor":4,"carSize":1,"carPosition":{"x":-1.8890697337962963,"y":-0.5987356680410879,"z":0},"carDirection":6},{"idCar":28,"carColor":11,"carSize":0,"carPosition":{"x":-0.3527063440393518,"y":-6.976921364113136,"z":0},"carDirection":6},{"idCar":27,"carColor":2,"carSize":0,"carPosition":{"x":1.3944786919487846,"y":-6.976923624674479,"z":0},"carDirection":6},{"idCar":26,"carColor":4,"carSize":1,"carPosition":{"x":1.1359303792317708,"y":0.25925925925925924,"z":0},"carDirection":6},{"idCar":25,"carColor":1,"carSize":1,"carPosition":{"x":-3.9406294646086515,"y":-4.085732919198495,"z":0},"carDirection":4},{"idCar":24,"carColor":4,"carSize":1,"carPosition":{"x":-5.656626100893374,"y":-1.3981029369212963,"z":0},"carDirection":4},{"idCar":23,"carColor":4,"carSize":1,"carPosition":{"x":3.946483470775463,"y":-2.6759259259259256,"z":0},"carDirection":0},{"idCar":21,"carColor":11,"carSize":0,"carPosition":{"x":-4.809628804524739,"y":-3.4459183304398144,"z":0},"carDirection":4},{"idCar":20,"carColor":2,"carSize":1,"carPosition":{"x":-0.8972625732421875,"y":-7.823922051323784,"z":0},"carDirection":2},{"idCar":19,"carColor":4,"carSize":1,"carPosition":{"x":1.0021079734519676,"y":-7.823923746744791,"z":0},"carDirection":6},{"idCar":18,"carColor":2,"carSize":1,"carPosition":{"x":1.5429297553168402,"y":-0.5987379286024305,"z":0},"carDirection":6},{"idCar":17,"carColor":1,"carSize":1,"carPosition":{"x":3.946480079933449,"y":-5.974110921223958,"z":0},"carDirection":0},{"idCar":16,"carColor":3,"carSize":0,"carPosition":{"x":3.064663357204861,"y":-6.976925885235821,"z":0},"carDirection":6},{"idCar":15,"carColor":11,"carSize":0,"carPosition":{"x":4.814814814814815,"y":-5.0740740740740735,"z":0},"carDirection":0},{"idCar":14,"carColor":2,"carSize":1,"carPosition":{"x":1.1359326397931133,"y":1.2839638038917824,"z":0},"carDirection":6},{"idCar":13,"carColor":4,"carSize":1,"carPosition":{"x":5.792668095341435,"y":-2.8391135886863426,"z":0},"carDirection":4},{"idCar":12,"carColor":3,"carSize":1,"carPosition":{"x":4.814814814814815,"y":-3.4074074074074074,"z":0},"carDirection":0},{"idCar":11,"carColor":3,"carSize":1,"carPosition":{"x":-5.656627655029297,"y":-2.9491023310908564,"z":0},"carDirection":4},{"idCar":10,"carColor":2,"carSize":1,"carPosition":{"x":-1.3170697247540508,"y":0.2922645851417824,"z":0},"carDirection":2},{"idCar":8,"carColor":2,"carSize":1,"carPosition":{"x":-3.9406308774594905,"y":-5.788917258933738,"z":0},"carDirection":4},{"idCar":5,"carColor":4,"carSize":1,"carPosition":{"x":-1.3170668990523726,"y":1.2949670862268519,"z":0},"carDirection":2},{"idCar":4,"carColor":7,"carSize":0,"carPosition":{"x":-2.0778913144712092,"y":-6.976919668692129,"z":0},"carDirection":6},{"idCar":2,"carColor":1,"carSize":1,"carPosition":{"x":5.792670355902778,"y":-1.3431125217013888,"z":0},"carDirection":0},{"idCar":1,"carColor":4,"carSize":1,"carPosition":{"x":-4.809630499945746,"y":-5.226104171187789,"z":0},"carDirection":4}],"GarageInfo":[],"ConveyorBeltInfo":[],"Group":[{"typeUse":4,"numberLose":-1,"listGroups":[],"dataCustom":"1_24_6-1-100,6-2-100,6-3-100,6-6-100_4_0*2_46_12-0-100,6-2-100,10-4-100,6-5-100,6-6-100,6-7-100_8_0*3_28_6-1-100,6-2-100,6-3-100,4-4-100,6-6-100_5_0*4_54_12-0-100,18-2-100,12-3-100,12-9-100_9_0*5_16_6-5-100,10-9-100_3_0*6_20_10-7-100,6-8-100,4-9-100_3_0*7_36_4-4-100,10-7-100,12-8-100,10-9-100_5_0*8_32_6-5-100,4-7-100,6-8-100,16-9-100_5_0*11_24_4-1-100,8-3-100,4-4-100,4-6-100,4-9-100_6_1*12_4_4-8-100_1_1"}]}}